{
  "type": "AdaptiveCard",
  "$schema": "http://adaptivecards.io/schemas/adaptive-card.json",
  "version": "1.2",
  "body": [
    {
      "type": "TextBlock",
      "text": "Horizontal alignment center",
      "size": "ExtraLarge"
    },
    {
      "type": "ColumnSet",
      "horizontalAlignment": "Center",
      "columns": [
        {
          "type": "Column",
          "items": [
            {
              "type": "ActionSet",
              "actions": [
                {
                  "type": "Action.Submit",
                  "title": "«",
                  "data": {
                    "action": "left"
                  }
                }
              ]
            }
          ],
          "spacing": "Small"
        },
        {
          "type": "Column",
          "items": [
            {
              "type": "ActionSet",
              "actions": [
                {
                  "type": "Action.Submit",
                  "title": "Center",
                  "data": {
                    "action": "center"
                  }
                }
              ]
            }
          ],
          "spacing": "Small"
        },
        {
          "type": "Column",
          "items": [
            {
              "type": "ActionSet",
              "actions": [
                {
                  "type": "Action.Submit",
                  "title": "»",
                  "data": {
                    "action": "right"
                  }
                }
              ]
            }
          ],
          "spacing": "Small"
        }
      ],
      "spacing": "Small"
    }
  ]
}